devops/__init__.py
devops/notifications.py
fintopia-0.0.1.dist-info/METADATA
fintopia-0.0.1.dist-info/WHEEL
fintopia-0.0.1.dist-info/top_level.txt
fintopia-0.0.1.dist-info/RECORD
